{
    "DNDConfig": null,
    "__UDWInstanceModelForRender__": true,
    "_height_": {
        "type": "string",
        "value": "16dp"
    },
    "_margin_": [
        0,
        0,
        0,
        0
    ],
    "_orientation_": 6,
    "_padding_": [
        0,
        0,
        0,
        0
    ],
    "_percent_": true,
    "_right_": {
        "type": "string",
        "value": "16dp"
    },
    "_skin_": "s94cdb65efdd4952844640b768507380",
    "_top_": {
        "type": "string",
        "value": "15dp"
    },
    "_width_": {
        "type": "string",
        "value": "95%"
    },
    "allboxes": [],
    "autogrowmode": 0,
    "canUpdateUI": true,
    "children": [
        "imgInfo",
        "btnDownload"
    ],
    "clipbounds": false,
    "containerweight": 100,
    "enablescrolling": true,
    "id": "flxDownload",
    "info": null,
    "iscustomlayout": false,
    "isvisible": true,
    "kuid": "bd3f0c4a6c2449959c567479eb317921",
    "layouttype": 3,
    "name": "kony.ui.FlexContainer",
    "parent": "flxUploadBulk",
    "pf": "frmUploadInvoices",
    "retaincontentalignment": false,
    "retainflexpositionproperties": false,
    "retainflowhorizontalalignment": false,
    "reverselayoutdirection": true,
    "snapgridsize": 10,
    "snaptogrid": true,
    "wType": "FlexContainer",
    "widgetalignment": 1
}