{
    "@class": "com.kony.gen.viz.model.component.KVizButton",
    "DNDConfig": null,
    "_height_": {
        "type": "string",
        "value": "75%"
    },
    "_margin_": [
        6,
        6,
        6,
        6
    ],
    "_padding_": [
        0,
        0,
        0,
        0
    ],
    "_skin_": "sfbd4234507b4b7f9c7a3538494271fb",
    "_text_": "تحقق",
    "_top_": {
        "type": "string",
        "value": "5%"
    },
    "_width_": {
        "type": "string",
        "value": "96%"
    },
    "canUpdateUI": true,
    "centerx": {
        "type": "string",
        "value": "50%"
    },
    "containerweight": 100,
    "contentalignment": 5,
    "displaytext": true,
    "focusskin": "se7990c90290425985c71de10dfeaf76",
    "id": "btnOtpConfirm",
    "info": null,
    "iscustomlayout": false,
    "isvisible": true,
    "kuid": "c6e94fe7807d4ee78c32e99761adc187",
    "name": "kony.ui.Button",
    "parent": "flxOtpBouttons",
    "pf": "frmULTUNRemittanceMoney",
    "retaincontentalignment": false,
    "retainflexpositionproperties": false,
    "wType": "Button",
    "zindex": 1
}