{
    "@class": "com.kony.gen.viz.model.component.KVizLabel",
    "DNDConfig": null,
    "__UDWInstanceModelForRender__": true,
    "_height_": {
        "type": "string",
        "value": "21dp"
    },
    "_left_": {
        "type": "string",
        "value": "0"
    },
    "_margin_": [
        1,
        1,
        1,
        1
    ],
    "_padding_": [
        0,
        0,
        0,
        0
    ],
    "_skin_": "sd6b83cb22494a4fa17d184477d96f98",
    "_text_": "L",
    "_top_": {
        "type": "string",
        "value": "0"
    },
    "_width_": {
        "type": "string",
        "value": "21dp"
    },
    "_wrapping_": 2,
    "android": {
        "textStyle": {
            "letterSpacing": 0,
            "strikeThrough": false
        }
    },
    "canUpdateUI": true,
    "containerweight": 100,
    "contentalignment": 5,
    "id": "lblRadioIcon2",
    "info": null,
    "ipad": {
        "psp": {
            "wrapping": 2
        }
    },
    "iphone": {
        "psp": {
            "wrapping": 2
        }
    },
    "iscustomlayout": false,
    "isvisible": true,
    "kuid": "b329f9cf185047f393e751c5010e1e9e",
    "name": "kony.ui.Label",
    "parent": "flxRadioIcon2",
    "pf": "frmDrawdownRequestStep1",
    "retaincontentalignment": false,
    "retainflexpositionproperties": false,
    "tooltip": "",
    "wType": "Label"
}