{
    "AS_Form_a76f752dd33240f280c250711abd1bd3": {
        "id": "AS_Form_a76f752dd33240f280c250711abd1bd3",
        "type": "ACTION_SEQUENCE",
        "params": [{
            "datatype": "collection",
            "name": "eventobject"
        }],
        "contextObj": {
            "name": "frmDrawdownRequestReviewAndSubmit",
            "type": "forms",
            "platform": "",
            "KUID": "i2b2be4c452a467f9417bad667c8da1e"
        },
        "language": "js",
        "actions": [{
            "id": "ADD_SNIPPET_aa625266c69745b1a4fb19ae9669dd63",
            "type": "ADD_SNIPPET",
            "codeSnippet": "this.init();",
            "parentId": null
        }]
    }
}