{
    "DNDConfig": null,
    "__UDWInstanceModelForRender__": true,
    "_bottom_": {
        "type": "string",
        "value": "20dp"
    },
    "_height_": {
        "type": "ref",
        "value": "preferred"
    },
    "_left_": {
        "type": "string",
        "value": "20dp"
    },
    "_margin_": [
        0,
        0,
        0,
        0
    ],
    "_orientation_": 6,
    "_padding_": [
        0,
        0,
        0,
        0
    ],
    "_percent_": true,
    "_top_": {
        "type": "string",
        "value": "8dp"
    },
    "_width_": {
        "type": "string",
        "value": "95%"
    },
    "allboxes": [],
    "autogrowmode": 1,
    "canUpdateUI": true,
    "children": [],
    "clipbounds": false,
    "containerweight": 100,
    "desktopweb": {
        "render": true
    },
    "enablescrolling": true,
    "id": "flxDetails",
    "info": null,
    "iscustomlayout": false,
    "isvisible": true,
    "kuid": "jcce5911ee2348beb88887b6a2806f7f",
    "layouttype": 4,
    "name": "kony.ui.FlexContainer",
    "parent": "flxDocMainContainer",
    "pf": "frmViewFundingRequest",
    "responsiveData": {
        "b1": {}
    },
    "retaincontentalignment": false,
    "retainflexpositionproperties": false,
    "retainflowhorizontalalignment": false,
    "snapgridsize": 10,
    "snaptogrid": true,
    "wType": "FlexContainer",
    "widgetalignment": 1
}