{
    "@class": "com.kony.gen.viz.model.component.KVizButton",
    "DNDConfig": null,
    "_height_": {
        "type": "string",
        "value": "40dp"
    },
    "_margin_": [
        6,
        6,
        6,
        6
    ],
    "_padding_": [
        10,
        0,
        10,
        0
    ],
    "_right_": {
        "type": "string",
        "value": "0dp"
    },
    "_skin_": "sa611611b2f24e93bcfd09e1606c01aa",
    "_text_": "",
    "_top_": {
        "type": "string",
        "value": "0"
    },
    "_width_": {
        "type": "string",
        "value": "150dp"
    },
    "canUpdateUI": true,
    "containerweight": 100,
    "contentalignment": 5,
    "desktopweb": {
        "psp": {}
    },
    "disabledSkins": {
        "focusSkin": "sfd0ce0d7f454c9f83c7e815a90a8a55",
        "hoverSkin": "s7ab6326aaf94c28b90b61fcb1b54547"
    },
    "displaytext": true,
    "focusskin": null,
    "id": "btnClear",
    "info": null,
    "iscustomlayout": false,
    "isvisible": true,
    "kuid": "d586ff9092f841399b116eae51286e65",
    "name": "kony.ui.Button",
    "paddinginpixel": true,
    "parent": "flxActions",
    "pf": "userwidgetmodel",
    "retaincontentalignment": false,
    "retainflexpositionproperties": false,
    "texti18n": "kony.mb.common.clear",
    "tooltip": "Clear",
    "wType": "Button"
}