{
    "DNDConfig": null,
    "__UDWInstanceModelForRender__": true,
    "_height_": {
        "type": "string",
        "value": "40dp"
    },
    "_margin_": [
        0,
        0,
        0,
        0
    ],
    "_orientation_": 6,
    "_padding_": [
        0,
        0,
        0,
        0
    ],
    "_percent_": true,
    "_skin_": "s5c80c509918419a8e0483b57abdf8f8",
    "_top_": {
        "type": "string",
        "value": "0dp"
    },
    "_width_": {
        "type": "string",
        "value": "40dp"
    },
    "allboxes": [],
    "autogrowmode": 0,
    "canUpdateUI": true,
    "centerx": {
        "type": "string",
        "value": "50%"
    },
    "children": [
        "lblIconQL1"
    ],
    "clipbounds": false,
    "containerweight": 100,
    "enablescrolling": true,
    "id": "flxIconQL1",
    "info": null,
    "iscustomlayout": false,
    "isvisible": true,
    "kuid": "d484196e289740cb874b0285a7c025e9",
    "layouttype": 2,
    "name": "kony.ui.FlexContainer",
    "parent": "flxQL1",
    "pf": "frmLendingDashboard",
    "retaincontentalignment": false,
    "retainflexpositionproperties": false,
    "retainflowhorizontalalignment": false,
    "snapgridsize": 10,
    "snaptogrid": true,
    "wType": "FlexContainer",
    "widgetalignment": 1
}